rulang/__init__.py
rulang/dependency_graph.py
rulang/engine.py
rulang/exceptions.py
rulang/path_resolver.py
rulang/visitor.py
rulang/workflows.py
rulang/grammar/BusinessRules.g4
rulang/grammar/__init__.py
rulang/grammar/.antlr/BusinessRules.interp
rulang/grammar/.antlr/BusinessRules.tokens
rulang/grammar/.antlr/BusinessRulesBaseListener.java
rulang/grammar/.antlr/BusinessRulesLexer.interp
rulang/grammar/.antlr/BusinessRulesLexer.java
rulang/grammar/.antlr/BusinessRulesLexer.tokens
rulang/grammar/.antlr/BusinessRulesListener.java
rulang/grammar/.antlr/BusinessRulesParser.java
rulang/grammar/generated/BusinessRules.interp
rulang/grammar/generated/BusinessRules.tokens
rulang/grammar/generated/BusinessRulesLexer.interp
rulang/grammar/generated/BusinessRulesLexer.py
rulang/grammar/generated/BusinessRulesLexer.tokens
rulang/grammar/generated/BusinessRulesListener.py
rulang/grammar/generated/BusinessRulesParser.py
rulang/grammar/generated/BusinessRulesVisitor.py
rulang/grammar/generated/__init__.py
rulang-1.0.0.dist-info/METADATA
rulang-1.0.0.dist-info/WHEEL
rulang-1.0.0.dist-info/licenses/LICENSE
rulang-1.0.0.dist-info/RECORD
