Metadata-Version: 2.4
Name: rulang
Version: 1.0.0
Summary: A lightweight DSL for business rules with dependency analysis
Project-URL: Homepage, https://github.com/Mohatje/rulang
Project-URL: Repository, https://github.com/Mohatje/rulang
Project-URL: Issues, https://github.com/Mohatje/rulang/issues
Author: Mohammed Al-Ogaili
License-Expression: MIT
License-File: LICENSE
Keywords: business-rules,domain-specific-language,dsl,rule-engine,rules
Classifier: Development Status :: 4 - Beta
Classifier: Intended Audience :: Developers
Classifier: License :: OSI Approved :: MIT License
Classifier: Programming Language :: Python :: 3
Classifier: Programming Language :: Python :: 3.12
Classifier: Programming Language :: Python :: 3.13
Classifier: Topic :: Software Development :: Libraries :: Python Modules
Requires-Python: >=3.12
Requires-Dist: antlr4-python3-runtime>=4.13.2
Provides-Extra: dev
Requires-Dist: antlr4-tools>=0.2.2; extra == 'dev'
Requires-Dist: bump-my-version>=0.28.0; extra == 'dev'
Requires-Dist: pytest-cov>=7.0.0; extra == 'dev'
Requires-Dist: pytest>=9.0.2; extra == 'dev'
